cforge/__init__.py
cforge/_version.py
cforge/common.py
cforge/config.py
cforge/credential_store.py
cforge/main.py
cforge/profile_utils.py
cforge/commands/__init__.py
cforge/commands/deploy/__init__.py
cforge/commands/deploy/deploy.py
cforge/commands/metrics/__init__.py
cforge/commands/metrics/metrics.py
cforge/commands/resources/__init__.py
cforge/commands/resources/a2a.py
cforge/commands/resources/mcp_servers.py
cforge/commands/resources/prompts.py
cforge/commands/resources/resources.py
cforge/commands/resources/tools.py
cforge/commands/resources/virtual_servers.py
cforge/commands/server/__init__.py
cforge/commands/server/serve.py
cforge/commands/settings/__init__.py
cforge/commands/settings/config_schema.py
cforge/commands/settings/export.py
cforge/commands/settings/import_cmd.py
cforge/commands/settings/login.py
cforge/commands/settings/logout.py
cforge/commands/settings/profiles.py
cforge/commands/settings/support_bundle.py
cforge/commands/settings/version.py
cforge/commands/settings/whoami.py
cforge-0.9.3.dist-info/licenses/LICENSE
cforge-0.9.3.dist-info/METADATA
cforge-0.9.3.dist-info/WHEEL
cforge-0.9.3.dist-info/entry_points.txt
cforge-0.9.3.dist-info/top_level.txt
cforge-0.9.3.dist-info/RECORD
