Metadata-Version: 2.4
Name: cforge
Version: 0.9.3
Summary: CLI for Context Forge allowing seamless management of local or hosted MCP and A2A resources.
Author-email: Gabe Goodhart <ghart@us.ibm.com>
Maintainer-email: Gabe Goodhart <ghart@us.ibm.com>
License-Expression: Apache-2.0
Project-URL: Homepage, https://ibm.github.io/mcp-context-forge/
Project-URL: Documentation, https://ibm.github.io/mcp-context-forge/
Project-URL: Repository, https://github.com/contextforge-org/contextforge-cli
Project-URL: Bug Tracker, https://github.com/contextforge-org/contextforge-cli/issues
Project-URL: Changelog, https://github.com/contextforge-org/contextforge-cli/blob/main/CHANGELOG.md
Keywords: MCP,API,gateway,proxy,tools,agents,agentic ai,model context protocol,multi-agent,fastapi,json-rpc,sse,websocket,federation,security,authentication
Classifier: Development Status :: 4 - Beta
Classifier: Intended Audience :: Developers
Classifier: Programming Language :: Python :: 3
Classifier: Programming Language :: Python :: 3.11
Classifier: Programming Language :: Python :: 3.12
Classifier: Programming Language :: Python :: 3.13
Classifier: Framework :: FastAPI
Classifier: Framework :: AsyncIO
Classifier: Topic :: Internet :: WWW/HTTP :: WSGI :: Application
Classifier: Topic :: Software Development :: Libraries :: Application Frameworks
Requires-Python: <3.14,>=3.11
License-File: LICENSE
Requires-Dist: rich>=13.9.4
Requires-Dist: typer>=0.20.0
Requires-Dist: mcp-contextforge-gateway>=0.9.0
Requires-Dist: cryptography>=44.0.0
Provides-Extra: dev
Requires-Dist: pytest>=8.4.2; extra == "dev"
Requires-Dist: pytest-cov>=7.0.0; extra == "dev"
Requires-Dist: pytest-html>=3.1.1; extra == "dev"
Requires-Dist: twine>=6.2.0; extra == "dev"
Requires-Dist: build>=1.3.0; extra == "dev"
Dynamic: license-file
